pypn_ref_geo-1.5.6.dist-info/licenses/LICENSE
ref_geo/__init__.py
ref_geo/commands.py
ref_geo/env.py
ref_geo/models.py
ref_geo/routes.py
ref_geo/schemas.py
ref_geo/utils.py
ref_geo/migrations/__init__.py
ref_geo/migrations/env.py
ref_geo/migrations/utils.py
ref_geo/migrations/data/__init__.py
ref_geo/migrations/data/ref_geo.sql
ref_geo/migrations/data/ref_geo_cor.sql
ref_geo/migrations/data/ref_geo_linear.sql
ref_geo/migrations/data/ref_geo_point.sql
ref_geo/migrations/versions/05a0ae652c13_ref_geo_french_regions_1970.py
ref_geo/migrations/versions/0dfdbfbccd63_ref_geo_french_municipalities.py
ref_geo/migrations/versions/10a587fb63d1_ref_geo_inpn_grids_20.py
ref_geo/migrations/versions/175cdb17343f_ref_geo_inpn_grids_2.py
ref_geo/migrations/versions/1fdac7036dd9_rewrite_fct_get_altitude_intersection.py
ref_geo/migrations/versions/31ca7fd0d2ea_added_l_areas_description.py
ref_geo/migrations/versions/3fdaa1805575_ref_geo_french_departments.py
ref_geo/migrations/versions/4882d6141a41_add_regions_in_area_types.py
ref_geo/migrations/versions/4d0c35ea0cfe_ref_geo_inpn_grids_50.py
ref_geo/migrations/versions/557aadcf2e45_add_missing_size_hierachy.py
ref_geo/migrations/versions/586613e2faeb_ref_geo_inpn_grids_1.py
ref_geo/migrations/versions/681306b27407_fix_altitude_trigger.py
ref_geo/migrations/versions/6afe74833ed0_ref_geo.py
ref_geo/migrations/versions/795f6ea8ec45_cor_linear_area.py
ref_geo/migrations/versions/7d6e98441e4c_ref_geo_inpn_grids_5.py
ref_geo/migrations/versions/99591aa2dcf8_add_missing_size_hierachy.py
ref_geo/migrations/versions/__init__.py
ref_geo/migrations/versions/bc2fcc772b46_geom_4326.py
ref_geo/migrations/versions/cb038e76d59c_fix_functions_local_srid.py
ref_geo/migrations/versions/d02f4563bebe_ref_geo_french_regions.py
ref_geo/migrations/versions/dea1645de8c0_ref_geo_point.py
ref_geo/migrations/versions/e0ac4c9f5c0a_add_indexes_on_fk_referencing_id_area.py
ref_geo/migrations/versions/e58071a29130_add_missing_size_hierachy.py
ref_geo/migrations/versions/ede150d9afd9_ref_geo_inpn_grids_10.py
pypn_ref_geo-1.5.6.dist-info/METADATA
pypn_ref_geo-1.5.6.dist-info/WHEEL
pypn_ref_geo-1.5.6.dist-info/entry_points.txt
pypn_ref_geo-1.5.6.dist-info/top_level.txt
pypn_ref_geo-1.5.6.dist-info/RECORD
