Metadata-Version: 2.4
Name: pypn-ref-geo
Version: 1.5.6
Summary: Référentiel géographique
Home-page: https://github.com/PnX-SI/RefGeo
Maintainer: Parcs nationaux des Écrins et des Cévennes
Maintainer-email: geonature@ecrins-parcnational.fr
Classifier: Development Status :: 1 - Planning
Classifier: Intended Audience :: Developers
Classifier: Natural Language :: English
Classifier: Programming Language :: Python :: 3
Classifier: Programming Language :: Python :: 3.9
Classifier: Programming Language :: Python :: 3.11
Classifier: License :: OSI Approved :: GNU Affero General Public License v3
Classifier: Operating System :: OS Independent
License-File: LICENSE
Requires-Dist: alembic
Requires-Dist: flask>=3.0
Requires-Dist: flask-sqlalchemy
Requires-Dist: flask-marshmallow
Requires-Dist: python-dotenv
Requires-Dist: sqlalchemy<2,>=1.4
Requires-Dist: utils-flask-sqlalchemy>=0.4.2
Requires-Dist: utils-flask-sqlalchemy-geo>=0.3.3
Requires-Dist: psycopg2
Requires-Dist: backports.entry-points-selectable
Provides-Extra: tests
Requires-Dist: pytest; extra == "tests"
Requires-Dist: pytest-flask; extra == "tests"
Requires-Dist: pytest-cov; extra == "tests"
Requires-Dist: jsonschema; extra == "tests"
Dynamic: classifier
Dynamic: description
Dynamic: description-content-type
Dynamic: home-page
Dynamic: license-file
Dynamic: maintainer
Dynamic: maintainer-email
Dynamic: provides-extra
Dynamic: requires-dist
Dynamic: summary
